{
    "disableAutoUpdate": false,
    "name": "gathering-markers",
    "author": "devnull0x00",
    "description": "Spawn item markers on gathering nodes and hide undesirable nodes.",
    "options": {
        "niceName": "Gathering Markers",
		"reloadable": true,
        "settingsVersion": 1,
        "settingsFile": "config.json",
        "settingsAutosaveOnClose": true
    },
    "servers": ["https://raw.githubusercontent.com/devnull0x00/gathering-markers/master/"],
    "supportUrl": "https://github.com/devnull0x00/gathering-markers/issues"
}